.hgignore
.travis.yml
AUTHORS
ChangeLog
LICENSE
README.md
Vagrantfile
pytest.ini
requirements.txt
setup.cfg
setup.py
tox.ini
bugs/issue-1bcdb58a5629019f1091e949a9f3560fd0467aaf.yaml
bugs/issue-337aeb65a7c5bfd42c3d6e1359491a74e0b24b97.yaml
bugs/issue-3dfcbb01a2a23b5f510049e545d99eb1d2995477.yaml
bugs/issue-4d2744d4c05a71219e4a1e726aeaf2f5102d1540.yaml
bugs/issue-7d0cd8473f1e2590312c58f1e45390575c403c4c.yaml
bugs/issue-993e4516369660523019b49776869c4ff234b9ae.yaml
bugs/issue-cb38db2784e88d3eae3c0cd2e8341ee5bc11e6e3.yaml
bugs/issue-cbeeca593c375b88547d126f3fed35d63f1b1f3e.yaml
bugs/issue-cf83ad674f295e906a9df5ed9344d2de5d8c3fd3.yaml
bugs/issue-ee3d2d54095854230c1573b120318ca1212ad461.yaml
bugs/project.yaml
zeroconf/__init__.py
zeroconf/linux.py
zeroconf/windows.py
zeroconf3.egg-info/PKG-INFO
zeroconf3.egg-info/SOURCES.txt
zeroconf3.egg-info/dependency_links.txt
zeroconf3.egg-info/not-zip-safe
zeroconf3.egg-info/pbr.json
zeroconf3.egg-info/requires.txt
zeroconf3.egg-info/top_level.txt