Metadata-Version: 1.1
Name: zeroconf3
Version: 2.0.5.dev17
Summary: Python3 version of Sebastien Boisgerault's python zeroconf library
Home-page: UNKNOWN
Author: David Francos
Author-email: opensource@davidfrancos.net
License: MIT
Keywords: ZeroConf
Platform: UNKNOWN
Classifier: Development Status :: 4 - Beta
Classifier: Environment :: Console
Classifier: Intended Audience :: Developers
Classifier: Intended Audience :: Information Technology
Classifier: License :: OSI Approved :: MIT License
Classifier: Operating System :: OS Independent
Classifier: Programming Language :: Python
